cava_nlp/__init__.py
cava_nlp/language.py
cava_nlp/context/__init__.py
cava_nlp/context/config.py
cava_nlp/context/context_resolver.py
cava_nlp/context/hooks.py
cava_nlp/context/registry.py
cava_nlp/context/profiles/clinical.json
cava_nlp/context/profiles/tests.json
cava_nlp/namespaces/__init__.py
cava_nlp/namespaces/constructs/value_extractor_constructs.py
cava_nlp/namespaces/core/loader.py
cava_nlp/namespaces/core/loading_helpers.py
cava_nlp/namespaces/core/namespace.py
cava_nlp/namespaces/core/registry.py
cava_nlp/namespaces/core/rule_config.py
cava_nlp/namespaces/core/validator.py
cava_nlp/namespaces/regex/__init__.py
cava_nlp/namespaces/regex/common.py
cava_nlp/namespaces/regex/datetime.py
cava_nlp/namespaces/regex/numeric.py
cava_nlp/namespaces/regex/units.py
cava_nlp/namespaces/rulesets/alk.json
cava_nlp/namespaces/rulesets/braf.json
cava_nlp/namespaces/rulesets/ecog.json
cava_nlp/namespaces/rulesets/egfr.json
cava_nlp/namespaces/rulesets/kras.json
cava_nlp/namespaces/rulesets/pdl1.json
cava_nlp/namespaces/rulesets/pgsga.json
cava_nlp/namespaces/rulesets/ros.json
cava_nlp/namespaces/rulesets/weight.json
cava_nlp/normalisation/__init__.py
cava_nlp/normalisation/normaliser.py
cava_nlp/normalisation/normaliser_factory.py
cava_nlp/rule_engine/__init__.py
cava_nlp/rule_engine/rule_engine.py
cava_nlp/rule_engine/rule_engine_factory.py
cava_nlp/rule_engine/value_resolver.py
cava_nlp/rule_engine/engine_config/core.yaml
cava_nlp/rule_engine/engine_config/default.yaml
cava_nlp/rule_engine/engine_config/dietetics.yaml
cava_nlp/structural/__init__.py
cava_nlp/structural/document_layout.py
cava_nlp/structural/document_layout_factory.py
cava_nlp/tokenization/__init__.py
cava_nlp/tokenization/_tokenizer_exceptions_list.py
cava_nlp/tokenization/builder.py
cava_nlp/tokenization/defaults.py
cava_nlp/tokenization/exceptions.py
cava_nlp/tokenization/preprocess.py
cava_nlp/tokenization/tokenizer_exceptions.py
cava_nlp-0.9.6.dist-info/licenses/LICENSE
cava_nlp-0.9.6.dist-info/METADATA
cava_nlp-0.9.6.dist-info/WHEEL
cava_nlp-0.9.6.dist-info/top_level.txt
cava_nlp-0.9.6.dist-info/RECORD
