Metadata-Version: 2.4
Name: cava-nlp
Version: 0.9.6
Summary: CaVa Platform Natural Language Processing spaCy components and pipeline
Requires-Python: <3.13,>=3.11
License-File: LICENSE
Requires-Dist: medspacy==1.3.1
Requires-Dist: striprtf>=0.0.2
Requires-Dist: python-dateutil==2.8.2
Requires-Dist: dateparser>=1.2.2
Requires-Dist: pyyaml>=6.0.3
Requires-Dist: urllib3>=2.6.0
Provides-Extra: docs
Requires-Dist: mkdocs>=1.6; extra == "docs"
Requires-Dist: mkdocs-material>=9.5; extra == "docs"
Requires-Dist: mkdocstrings[python]>=0.25; extra == "docs"
Requires-Dist: mkdocs-gen-files>=0.5; extra == "docs"
Requires-Dist: mkdocs-literate-nav>=0.6; extra == "docs"
Requires-Dist: mkdocs-section-index>=0.3; extra == "docs"
Requires-Dist: mkdocs-autorefs>=1.0; extra == "docs"
Requires-Dist: pymdown-extensions>=10.8; extra == "docs"
Requires-Dist: mkdocs-mermaid2-plugin>=1.2; extra == "docs"
Dynamic: license-file
